ekodb_client/__init__.py
ekodb_client/_ekodb_client.abi3.so
ekodb_client/stages.py
ekodb_client/utils.py
ekodb_client-0.8.0.dist-info/METADATA
ekodb_client-0.8.0.dist-info/WHEEL
ekodb_client-0.8.0.dist-info/RECORD
