Metadata-Version: 2.4
Name: ekodb_client
Version: 0.8.0
Classifier: Development Status :: 4 - Beta
Classifier: Intended Audience :: Developers
Classifier: License :: OSI Approved :: MIT License
Classifier: License :: OSI Approved :: Apache Software License
Classifier: Programming Language :: Python :: 3
Classifier: Programming Language :: Python :: 3.8
Classifier: Programming Language :: Python :: 3.9
Classifier: Programming Language :: Python :: 3.10
Classifier: Programming Language :: Python :: 3.11
Classifier: Programming Language :: Python :: 3.12
Classifier: Programming Language :: Rust
Requires-Dist: pytest>=7.0.0 ; extra == 'dev'
Requires-Dist: pytest-asyncio>=0.21.0 ; extra == 'dev'
Provides-Extra: dev
Summary: Python client for ekoDB - a high-performance document database
Keywords: database,ekodb,document-database,nosql
Author: ekoDB Team
License: MIT OR Apache-2.0
Requires-Python: >=3.8
Project-URL: Documentation, https://github.com/ekoDB/ekodb/tree/main/documentation
Project-URL: Homepage, https://github.com/ekoDB/ekodb
Project-URL: Repository, https://github.com/ekoDB/ekodb
